{
    "en": {
       "title": "Privacy policy",
       "policies": [
        {
            "title": "HOW LONG WE KEEP PERSONAL DATA:",
            "desc": "Lorem ipsum dolor sit amet, consectetur adipiscing elit, sed do eiusmod tempor incididunt ut labore et dolore magna aliqua. Velit laoreet id donec ultrices tincidunt. Fermentum posuere urna nec tincidunt praesent semper feugiat nibh sed. Ac feugiat sed lectus vestibulum mattis ullamcorper velit. Fames ac turpis egestas sed tempus urna et pharetra. Vulputate dignissim suspendisse in est ante in nibh mauris. nibh tortor id aliquet lectus. Ullamcorper eget nulla facilisi etiam dignissim. Facilisi cras fermentum odio eu feugiat pretium nibh ipsum. Orci phasellus egestas tellus rutrum tellus pellentesque.  Lorem ipsum dolor sit amet, consectetur adipiscing elit, sed do eiusmod tempor incididunt ut labore et dolore magna aliqua. Velit laoreet id donec ultrices tincidunt. Fermentum posuere urna nec tincidunt praesent semper feugiat nibh sed. Ac feugiat sed lectus vestibulum mattis ullamcorper velit. Fames ac turpis egestas sed tempus urna et pharetra. Vulputate dignissim suspendisse in est ante in nibh mauris. nibh tortor id aliquet lectus. Ullamcorper eget nulla facilisi etiam dignissim. Facilisi cras fermentum odio eu feugiat pretium nibh ipsum. Orci phasellus egestas tellus rutrum tellus pellentesque.Lorem ipsum dolor sit amet, consectetur adipiscing elit, sed do eiusmod tempor incididunt ut labore et dolore magna aliqua. Velit laoreet id donec ultrices tincidunt. Fermentum posuere urna nec tincidunt praesent semper feugiat nibh sed. Ac feugiat sed lectus vestibulum mattis ullamcorper velit. Fames ac turpis egestas sed tempus urna et pharetra. Vulputate dignissim suspendisse in est ante in nibh mauris. nibh tortor id aliquet lectus. Ullamcorper eget nulla facilisi etiam dignissim. Facilisi cras fermentum odio eu feugiat pretium nibh ipsum. Orci phasellus egestas tellus rutrum tellus pellentesque. Sit amet mattis vulputate enim nulla aliquet. Semper risus in hendrerit gravida rutrum quisque."
        },
        {
            "title": "SHARING PERSONAL DATA WITH THIRD PARTIES:",
            "desc": "Lorem ipsum dolor sit amet, consectetur adipiscing elit, sed do eiusmod tempor incididunt ut labore et dolore magna aliqua. Velit laoreet id donec ultrices tincidunt. Fermentum posuere urna nec tincidunt praesent semper feugiat nibh sed. Ac feugiat sed lectus vestibulum mattis ullamcorper velit. Fames ac turpis egestas sed tempus urna et pharetra. Vulputate dignissim suspendisse in est ante in nibh mauris. nibh tortor id aliquet lectus. Ullamcorper eget nulla facilisi etiam dignissim. Facilisi cras fermentum odio eu feugiat pretium nibh ipsum. Orci phasellus egestas tellus rutrum tellus pellentesque.  Lorem ipsum dolor sit amet, consectetur adipiscing elit, sed do eiusmod tempor incididunt ut labore et dolore magna aliqua. Velit laoreet id donec ultrices tincidunt. Fermentum posuere urna nec tincidunt praesent semper feugiat nibh sed. Ac feugiat sed lectus vestibulum mattis ullamcorper velit. Fames ac turpis egestas sed tempus urna et pharetra. Vulputate dignissim suspendisse in est ante in nibh mauris. nibh tortor id aliquet lectus. Ullamcorper eget nulla facilisi etiam dignissim. Facilisi cras fermentum odio eu feugiat pretium nibh ipsum. Orci phasellus egestas tellus rutrum tellus pellentesque.Lorem ipsum dolor sit amet, consectetur adipiscing elit, sed do eiusmod tempor incididunt ut labore et dolore magna aliqua. Velit laoreet id donec ultrices tincidunt. Fermentum posuere urna nec tincidunt praesent semper feugiat nibh sed. Ac feugiat sed lectus vestibulum mattis ullamcorper velit. Fames ac turpis egestas sed tempus urna et pharetra. Vulputate dignissim suspendisse in est ante in nibh mauris. nibh tortor id aliquet lectus. Ullamcorper eget nulla facilisi etiam dignissim. Facilisi cras fermentum odio eu feugiat pretium nibh ipsum. Orci phasellus egestas tellus rutrum tellus pellentesque. Sit amet mattis vulputate enim nulla aliquet. Semper risus in hendrerit gravida rutrum quisque."
        }
       ]
    }
}
